{
    "title": "Uralic Typological database - UraTyp",
    "access_right": "open",
    "keywords": [
        "cldf:StructureDataset",
        "linguistics"
    ],
    "upload_type": "dataset",
    "description": "<p>Cite the source of the dataset as:</p>\n\n<blockquote>\n<p>Miina Norvik, Robert Forkel, Uldis Balodis, Jeremy Bradley, Michael Dunn, Ilya Egorov, Idaliia Feodotova, Terhi Honkola, Atte Huhtala, Yingqi Jing, Markus Juutinen, Olle Kejonen, Gerson Klumpp, Richard Kowalik, Nikolay Kuznetsov, Miika Lehtinen, Helle Metslang, Merit Niinem\u00e4gi, Karl Pajusalu, Minerva Piha, Przemys\u0142aw Podle\u015bny, Mihkel R\u00fcnkla, Eva Saar, Sirkka Saarinen, Denys Teptiuk, Pire Teras, Marili Tomingas, Tuuli Tuisk, Janek Vaab, &amp; Outi Vesakoski. (2026). Uralic Typological database - UraTyp (v2.0) [Data set]. Zenodo. https://doi.org/10.5281/zenodo.6392555</p>\n</blockquote>",
    "license": {
        "id": "CC-BY-4.0"
    },
    "creators": [
        {
            "name": "Miina Norvik"
        },
        {
            "name": "Robert Forkel"
        },
        {
            "name": "Uldis Balodis"
        },
        {
            "name": "Jeremy Bradley"
        },
        {
            "name": "Michael Dunn"
        },
        {
            "name": "Ilya Egorov"
        },
        {
            "name": "Idaliia Feodotova"
        },
        {
            "name": "Terhi Honkola"
        },
        {
            "name": "Atte Huhtala"
        },
        {
            "name": "Yingqi Jing"
        },
        {
            "name": "Markus Juutinen"
        },
        {
            "name": "Olle Kejonen"
        },
        {
            "name": "Gerson Klumpp"
        },
        {
            "name": "Richard Kowalik"
        },
        {
            "name": "Nikolay Kuznetsov"
        },
        {
            "name": "Miika Lehtinen"
        },
        {
            "name": "Helle Metslang"
        },
        {
            "name": "Merit Niinem\u00e4gi"
        },
        {
            "name": "Karl Pajusalu"
        },
        {
            "name": "Minerva Piha"
        },
        {
            "name": "Przemys\u0142aw Podle\u015bny"
        },
        {
            "name": "Mihkel R\u00fcnkla"
        },
        {
            "name": "Eva Saar"
        },
        {
            "name": "Sirkka Saarinen"
        },
        {
            "name": "Denys Teptiuk"
        },
        {
            "name": "Pire Teras"
        },
        {
            "name": "Marili Tomingas"
        },
        {
            "name": "Tuuli Tuisk"
        },
        {
            "name": "Janek Vaab"
        },
        {
            "name": "Outi Vesakoski"
        }
    ]
}